Metadata-Version: 2.4
Name: pytestomatio
Version: 2.10.2
Summary: Pytest plugin to sync test with testomat.io
Author: Oleksii Ostapov, TikoQA
Project-URL: Testomat.io, https://testomat.io/
Project-URL: Homepage, https://github.com/testomatio/pytestomatio
Project-URL: Bug Tracker, https://github.com/testomatio/pytestomatio/issues
Classifier: Framework :: Pytest
Classifier: Programming Language :: Python :: 3
Classifier: License :: OSI Approved :: MIT License
Classifier: Operating System :: OS Independent
Requires-Python: >=3.10
License-File: LICENSE
Requires-Dist: requests>=2.32.4
Requires-Dist: pytest>=8.4.1
Requires-Dist: boto3>=1.35.0
Requires-Dist: libcst>=1.4.0
Requires-Dist: commitizen>=4.8.3
Requires-Dist: autopep8>=2.3.2
Provides-Extra: dev
Requires-Dist: pytest>=8.4.1; extra == "dev"
Requires-Dist: pytest-testdox>=3.1.0; extra == "dev"
Requires-Dist: pytest-xdist>=3.6.0; extra == "dev"
Requires-Dist: python-dotenv>=1.0.1; extra == "dev"
Requires-Dist: toml>=0.10.2; extra == "dev"
Dynamic: license-file
